adcpreader/__init__.py
adcpreader/coroutine.py
adcpreader/rdi_backscatter.py
adcpreader/rdi_corrections.py
adcpreader/rdi_datafuse.py
adcpreader/rdi_qc.py
adcpreader/rdi_reader.py
adcpreader/rdi_transforms.py
adcpreader/rdi_writer.py
adcpreader-0.2.1.dist-info/COPYING
adcpreader-0.2.1.dist-info/METADATA
adcpreader-0.2.1.dist-info/WHEEL
adcpreader-0.2.1.dist-info/top_level.txt
adcpreader-0.2.1.dist-info/RECORD
