Metadata-Version: 2.1
Name: adcpreader
Version: 0.2.1
Summary: A python module to access binary data files generated by RDI ADCPs
Home-page: https://adcpreader.readthedocs.io/en/latest/
Author: Lucas Merckelbach
Author-email: lucas.merckelbach@hereon.de
Classifier: Programming Language :: Python :: 3
Classifier: Intended Audience :: Science/Research
Classifier: License :: OSI Approved :: GNU General Public License v3 (GPLv3)
Classifier: Operating System :: POSIX
License-File: COPYING
Requires-Dist: numpy
Requires-Dist: scipy
Requires-Dist: gsw
Requires-Dist: netCDF4
